./.gitignore
./PKG-INFO
./README.md
./__init__.py
./config.py
./pyproject.toml
./transport.py
rpp_mesh-0.1.0.dist-info/METADATA
rpp_mesh-0.1.0.dist-info/WHEEL
rpp_mesh-0.1.0.dist-info/RECORD
