Metadata-Version: 2.4
Name: rpp-mesh
Version: 0.1.0
Summary: RPP Mesh - Consent-aware overlay network extension for RPP
Project-URL: Homepage, https://github.com/anywave/rpp-spec
Project-URL: Documentation, https://github.com/anywave/rpp-spec/blob/master/spec/extensions/MESH.md
Project-URL: Repository, https://github.com/anywave/rpp-spec
Project-URL: Issues, https://github.com/anywave/rpp-spec/issues
Author: Alexander Liam Lennon
License-Expression: Apache-2.0
Keywords: consent,mesh,overlay-network,routing,rpp
Classifier: Development Status :: 3 - Alpha
Classifier: Environment :: Console
Classifier: Intended Audience :: Developers
Classifier: License :: OSI Approved :: Apache Software License
Classifier: Operating System :: OS Independent
Classifier: Programming Language :: Python :: 3
Classifier: Programming Language :: Python :: 3.9
Classifier: Programming Language :: Python :: 3.10
Classifier: Programming Language :: Python :: 3.11
Classifier: Programming Language :: Python :: 3.12
Classifier: Programming Language :: Python :: 3.13
Classifier: Topic :: System :: Networking
Classifier: Typing :: Typed
Requires-Python: >=3.9
Requires-Dist: rpp-protocol>=0.1.9
Provides-Extra: dev
Requires-Dist: pytest-asyncio>=0.21.0; extra == 'dev'
Requires-Dist: pytest>=7.0; extra == 'dev'
Provides-Extra: websockets
Requires-Dist: websockets>=11.0; extra == 'websockets'
